{
	"animations": [
		{
			"loop": true,
			"offsets": [
				2,
				-139
			],
			"anim": "idle",
			"fps": 11,
			"name": "Sonic OMT 1 idle",
			"indices": [
				1,
				2,
				3,
				4,
				5,
				6,
				5,
				5,
				6
			]
		},
		{
			"loop": false,
			"offsets": [
				0,
				-27
			],
			"anim": "singUP",
			"fps": 25,
			"name": "Sonic OMT 1 Up",
			"indices": []
		},
		{
			"loop": false,
			"offsets": [
				10,
				-147
			],
			"anim": "singRIGHT",
			"fps": 24,
			"name": "Sonic OMT 1 right",
			"indices": []
		},
		{
			"loop": false,
			"offsets": [
				109,
				-148
			],
			"anim": "singDOWN",
			"fps": 24,
			"name": "Sonic OMT 1 down",
			"indices": []
		},
		{
			"loop": false,
			"offsets": [
				0,
				-139
			],
			"anim": "singLEFT",
			"fps": 24,
			"name": "Sonic OMT 1 left",
			"indices": []
		},
		{
			"loop": false,
			"offsets": [
				110,
				-147
			],
			"anim": "singDOWN-alt",
			"fps": 14,
			"name": "Sonic OMT 1 Risa",
			"indices": []
		}
	],
	"no_antialiasing": true,
	"image": "characters/sonic omt gone",
	"position": [
		4700,
		356
	],
	"healthicon": "icon-omt",
	"flip_x": false,
	"healthbar_colors": [
		0,
		0,
		75
	],
	"camera_position": [
		-390,
		0
	],
	"sing_duration": 6.1,
	"scale": 8.00000000000001
}